CHANGELOG.txt
minifb.py
setup.cfg
setup.py
minifb.egg-info/PKG-INFO
minifb.egg-info/SOURCES.txt
minifb.egg-info/dependency_links.txt
minifb.egg-info/top_level.txt
minifb.egg-info/zip-safe